source/__init__.py
source/main.py
st/__init__.py
st/main.py
st/st.py
st_kickoff-0.2.dist-info/LICENSE
st_kickoff-0.2.dist-info/METADATA
st_kickoff-0.2.dist-info/WHEEL
st_kickoff-0.2.dist-info/entry_points.txt
st_kickoff-0.2.dist-info/top_level.txt
st_kickoff-0.2.dist-info/RECORD
