Metadata-Version: 2.1
Name: st-kickoff
Version: 0.2
Summary: st is a CLI that helps you kick-off a new Streamlit project          so you can start crafting the app as soon as possible!
Home-page: https://github.com/arnaudmiribel/st
Author: Arnaud Miribel
Author-email: arnaudmiribel@gmail.com
License: MIT
Keywords: streamlit cli
Platform: UNKNOWN
Classifier: Programming Language :: Python :: 3
Classifier: License :: OSI Approved :: MIT License
License-File: LICENSE
Requires-Dist: click (==7.1.2)
Requires-Dist: streamlit
